.gitignore
README.md
demo.py
requirements.txt
sample.png
setup.py
soco_clip/__init__.py
soco_clip/soco_clip.py
soco_clip/util.py
soco_clip.egg-info/PKG-INFO
soco_clip.egg-info/SOURCES.txt
soco_clip.egg-info/dependency_links.txt
soco_clip.egg-info/requires.txt
soco_clip.egg-info/top_level.txt
soco_clip/__pycache__/__init__.cpython-36.pyc
soco_clip/__pycache__/__init__.cpython-37.pyc
soco_clip/__pycache__/soco_clip.cpython-36.pyc
soco_clip/__pycache__/soco_clip.cpython-37.pyc
soco_clip/clip/__init__.py
soco_clip/clip/bpe_simple_vocab_16e6.txt.gz
soco_clip/clip/clip.py
soco_clip/clip/model.py
soco_clip/clip/simple_tokenizer.py
soco_clip/clip/__pycache__/__init__.cpython-36.pyc
soco_clip/clip/__pycache__/__init__.cpython-37.pyc
soco_clip/clip/__pycache__/clip.cpython-36.pyc
soco_clip/clip/__pycache__/clip.cpython-37.pyc
soco_clip/clip/__pycache__/model.cpython-36.pyc
soco_clip/clip/__pycache__/model.cpython-37.pyc
soco_clip/clip/__pycache__/simple_tokenizer.cpython-36.pyc
soco_clip/clip/__pycache__/simple_tokenizer.cpython-37.pyc
soco_clip/models/__init__.py
soco_clip/models/model.py
soco_clip/models/wrapper.py
soco_clip/models/__pycache__/__init__.cpython-36.pyc
soco_clip/models/__pycache__/__init__.cpython-37.pyc
soco_clip/models/__pycache__/model.cpython-36.pyc
soco_clip/models/__pycache__/model.cpython-37.pyc
soco_clip/models/__pycache__/wrapper.cpython-36.pyc
soco_clip/models/__pycache__/wrapper.cpython-37.pyc
soco_clip/models/__pycache__/wrapper2.cpython-37.pyc
soco_clip/models/configs/RN.yaml
soco_clip/models/configs/ViT.yaml
soco_clip/models/configs/__init__.py