Metadata-Version: 2.1
Name: soco-clip
Version: 0.0.9
Summary: OpenAI CLIP wrapper
Home-page: https://www.soco.ai
Author: kyusonglee
License: UNKNOWN
Platform: UNKNOWN
Classifier: Programming Language :: Python :: 3
Classifier: License :: Free for non-commercial use
Classifier: Operating System :: OS Independent
